Workbook

Sheet Inputs
A1: Input | B1: Value | C1: Note
A2: Purchase price (local currency) | B2: 3500000
A3: Down payment % | B3: 0.3
A4: Closing costs % (of purchase) | B4: 0.06
A5: Loan interest rate % (annual) | B5: 10
A6: Loan term (years) | B6: 20
A7: Monthly rent (year 1) | B7: 25000
A8: Rent growth % (annual) | B8: 0.03
A9: Vacancy % | B9: 0.05
A10: Operating expenses % (of gross rent) | B10: 0.25
A11: Holding period (years) | B11: 10
A12: Exit: sale price growth % (from purchase, per year) | B12: 0.02

Sheet Loan
A1: Period | B1: Payment | C1: Principal | D1: Interest | E1: Balance
A2: 1 | B2: =-PMT(Inputs!$B$5/100/12,Inputs!$B$6*12,(Inputs!$B$2*(1-Inputs!$B$3))) | C2: =PPMT(Inputs!$B$5/100/12,A2,Inputs!$B$6*12,(Inputs!$B$2*(1-Inputs!$B$3))) | D2: =IPMT(Inputs!$B$5/100/12,A2,Inputs!$B$6*12,(Inputs!$B$2*(1-Inputs!$B$3))) | E2: =(Inputs!$B$2*(1-Inputs!$B$3))+C2
A3: 2 | B3: =-PMT(Inputs!$B$5/100/12,Inputs!$B$6*12,(Inputs!$B$2*(1-Inputs!$B$3))) | C3: =PPMT(Inputs!$B$5/100/12,A3,Inputs!$B$6*12,(Inputs!$B$2*(1-Inputs!$B$3))) | D3: =IPMT(Inputs!$B$5/100/12,A3,Inputs!$B$6*12,(Inputs!$B$2*(1-Inputs!$B$3))) | E3: =E2+C3
A4: 3 | B4: =-PMT(Inputs!$B$5/100/12,Inputs!$B$6*12,(Inputs!$B$2*(1-Inputs!$B$3))) | C4: =PPMT(Inputs!$B$5/100/12,A4,Inputs!$B$6*12,(Inputs!$B$2*(1-Inputs!$B$3))) | D4: =IPMT(Inputs!$B$5/100/12,A4,Inputs!$B$6*12,(Inputs!$B$2*(1-Inputs!$B$3))) | E4: =E3+C4
A5: 4 | B5: =-PMT(Inputs!$B$5/100/12,Inputs!$B$6*12,(Inputs!$B$2*(1-Inputs!$B$3))) | C5: =PPMT(Inputs!$B$5/100/12,A5,Inputs!$B$6*12,(Inputs!$B$2*(1-Inputs!$B$3))) | D5: =IPMT(Inputs!$B$5/100/12,A5,Inputs!$B$6*12,(Inputs!$B$2*(1-Inputs!$B$3))) | E5: =E4+C5
A6: 5 | B6: =-PMT(Inputs!$B$5/100/12,Inputs!$B$6*12,(Inputs!$B$2*(1-Inputs!$B$3))) | C6: =PPMT(Inputs!$B$5/100/12,A6,Inputs!$B$6*12,(Inputs!$B$2*(1-Inputs!$B$3))) | D6: =IPMT(Inputs!$B$5/100/12,A6,Inputs!$B$6*12,(Inputs!$B$2*(1-Inputs!$B$3))) | E6: =E5+C6
A7: 6 | B7: =-PMT(Inputs!$B$5/100/12,Inputs!$B$6*12,(Inputs!$B$2*(1-Inputs!$B$3))) | C7: =PPMT(Inputs!$B$5/100/12,A7,Inputs!$B$6*12,(Inputs!$B$2*(1-Inputs!$B$3))) | D7: =IPMT(Inputs!$B$5/100/12,A7,Inputs!$B$6*12,(Inputs!$B$2*(1-Inputs!$B$3))) | E7: =E6+C7
A8: 7 | B8: =-PMT(Inputs!$B$5/100/12,Inputs!$B$6*12,(Inputs!$B$2*(1-Inputs!$B$3))) | C8: =PPMT(Inputs!$B$5/100/12,A8,Inputs!$B$6*12,(Inputs!$B$2*(1-Inputs!$B$3))) | D8: =IPMT(Inputs!$B$5/100/12,A8,Inputs!$B$6*12,(Inputs!$B$2*(1-Inputs!$B$3))) | E8: =E7+C8
A9: 8 | B9: =-PMT(Inputs!$B$5/100/12,Inputs!$B$6*12,(Inputs!$B$2*(1-Inputs!$B$3))) | C9: =PPMT(Inputs!$B$5/100/12,A9,Inputs!$B$6*12,(Inputs!$B$2*(1-Inputs!$B$3))) | D9: =IPMT(Inputs!$B$5/100/12,A9,Inputs!$B$6*12,(Inputs!$B$2*(1-Inputs!$B$3))) | E9: =E8+C9
A10: 9 | B10: =-PMT(Inputs!$B$5/100/12,Inputs!$B$6*12,(Inputs!$B$2*(1-Inputs!$B$3))) | C10: =PPMT(Inputs!$B$5/100/12,A10,Inputs!$B$6*12,(Inputs!$B$2*(1-Inputs!$B$3))) | D10: =IPMT(Inputs!$B$5/100/12,A10,Inputs!$B$6*12,(Inputs!$B$2*(1-Inputs!$B$3))) | E10: =E9+C10
A11: 10 | B11: =-PMT(Inputs!$B$5/100/12,Inputs!$B$6*12,(Inputs!$B$2*(1-Inputs!$B$3))) | C11: =PPMT(Inputs!$B$5/100/12,A11,Inputs!$B$6*12,(Inputs!$B$2*(1-Inputs!$B$3))) | D11: =IPMT(Inputs!$B$5/100/12,A11,Inputs!$B$6*12,(Inputs!$B$2*(1-Inputs!$B$3))) | E11: =E10+C11
A12: 11 | B12: =-PMT(Inputs!$B$5/100/12,Inputs!$B$6*12,(Inputs!$B$2*(1-Inputs!$B$3))) | C12: =PPMT(Inputs!$B$5/100/12,A12,Inputs!$B$6*12,(Inputs!$B$2*(1-Inputs!$B$3))) | D12: =IPMT(Inputs!$B$5/100/12,A12,Inputs!$B$6*12,(Inputs!$B$2*(1-Inputs!$B$3))) | E12: =E11+C12
A13: 12 | B13: =-PMT(Inputs!$B$5/100/12,Inputs!$B$6*12,(Inputs!$B$2*(1-Inputs!$B$3))) | C13: =PPMT(Inputs!$B$5/100/12,A13,Inputs!$B$6*12,(Inputs!$B$2*(1-Inputs!$B$3))) | D13: =IPMT(Inputs!$B$5/100/12,A13,Inputs!$B$6*12,(Inputs!$B$2*(1-Inputs!$B$3))) | E13: =E12+C13
A14: 13 | B14: =-PMT(Inputs!$B$5/100/12,Inputs!$B$6*12,(Inputs!$B$2*(1-Inputs!$B$3))) | C14: =PPMT(Inputs!$B$5/100/12,A14,Inputs!$B$6*12,(Inputs!$B$2*(1-Inputs!$B$3))) | D14: =IPMT(Inputs!$B$5/100/12,A14,Inputs!$B$6*12,(Inputs!$B$2*(1-Inputs!$B$3))) | E14: =E13+C14
... A21: 20 | B21: =-PMT(Inputs!$B$5/100/12,Inputs!$B$6*12,(Inputs!$B$2*(1-Inputs!$B$3))) | C21: =PPMT(Inputs!$B$5/100/12,A21,Inputs!$B$6*12,(Inputs!$B$2*(1-Inputs!$B$3))) | D21: =IPMT(Inputs!$B$5/100/12,A21,Inputs!$B$6*12,(Inputs!$B$2*(1-Inputs!$B$3))) | E21: =E20+C21

Sheet Cash Flow
A1: Year | B1: Gross Rent | C1: Vacancy | D1: Effective Rent | E1: OpEx | F1: NOI | G1: Debt Service | H1: Levered CF | I1: Sale Proceeds | J1: Total CF | K1: Cumulative CF
A2: 0 | B2: Initial | H2: =-(=Inputs!$B$2*Inputs!$B$3+Inputs!$B$2*Inputs!$B$4) | I2: 0 | J2: =H2+I2 | K2: =J2
A3: 1 | B3: =12*Inputs!$B$7*POWER(1+Inputs!$B$8,A3-1) | C3: =-B3*Inputs!$B$9 | D3: =B3+C3 | E3: =-B3*Inputs!$B$10 | F3: =D3+E3 | G3: =-12*Loan!$B$2 | H3: =F3+G3 | I3: =IF(A3=Inputs!$B$11,Inputs!$B$2*POWER(1+Inputs!$B$12,Inputs!$B$11)-FV(Inputs!$B$5/100/12,Inputs!$B$11*12,PMT(Inputs!$B$5/100/12,Inputs!$B$6*12,-Inputs!$B$2*(1-Inputs!$B$3)),-Inputs!$B$2*(1-Inputs!$B$3)),0) | J3: =H3+I3 | K3: =K2+J3
A4: 2 | B4: =12*Inputs!$B$7*POWER(1+Inputs!$B$8,A4-1) | C4: =-B4*Inputs!$B$9 | D4: =B4+C4 | E4: =-B4*Inputs!$B$10 | F4: =D4+E4 | G4: =-12*Loan!$B$2 | H4: =F4+G4 | I4: =IF(A4=Inputs!$B$11,Inputs!$B$2*POWER(1+Inputs!$B$12,Inputs!$B$11)-FV(Inputs!$B$5/100/12,Inputs!$B$11*12,PMT(Inputs!$B$5/100/12,Inputs!$B$6*12,-Inputs!$B$2*(1-Inputs!$B$3)),-Inputs!$B$2*(1-Inputs!$B$3)),0) | J4: =H4+I4 | K4: =K3+J4
A5: 3 | B5: =12*Inputs!$B$7*POWER(1+Inputs!$B$8,A5-1) | C5: =-B5*Inputs!$B$9 | D5: =B5+C5 | E5: =-B5*Inputs!$B$10 | F5: =D5+E5 | G5: =-12*Loan!$B$2 | H5: =F5+G5 | I5: =IF(A5=Inputs!$B$11,Inputs!$B$2*POWER(1+Inputs!$B$12,Inputs!$B$11)-FV(Inputs!$B$5/100/12,Inputs!$B$11*12,PMT(Inputs!$B$5/100/12,Inputs!$B$6*12,-Inputs!$B$2*(1-Inputs!$B$3)),-Inputs!$B$2*(1-Inputs!$B$3)),0) | J5: =H5+I5 | K5: =K4+J5
A6: 4 | B6: =12*Inputs!$B$7*POWER(1+Inputs!$B$8,A6-1) | C6: =-B6*Inputs!$B$9 | D6: =B6+C6 | E6: =-B6*Inputs!$B$10 | F6: =D6+E6 | G6: =-12*Loan!$B$2 | H6: =F6+G6 | I6: =IF(A6=Inputs!$B$11,Inputs!$B$2*POWER(1+Inputs!$B$12,Inputs!$B$11)-FV(Inputs!$B$5/100/12,Inputs!$B$11*12,PMT(Inputs!$B$5/100/12,Inputs!$B$6*12,-Inputs!$B$2*(1-Inputs!$B$3)),-Inputs!$B$2*(1-Inputs!$B$3)),0) | J6: =H6+I6 | K6: =K5+J6
A7: 5 | B7: =12*Inputs!$B$7*POWER(1+Inputs!$B$8,A7-1) | C7: =-B7*Inputs!$B$9 | D7: =B7+C7 | E7: =-B7*Inputs!$B$10 | F7: =D7+E7 | G7: =-12*Loan!$B$2 | H7: =F7+G7 | I7: =IF(A7=Inputs!$B$11,Inputs!$B$2*POWER(1+Inputs!$B$12,Inputs!$B$11)-FV(Inputs!$B$5/100/12,Inputs!$B$11*12,PMT(Inputs!$B$5/100/12,Inputs!$B$6*12,-Inputs!$B$2*(1-Inputs!$B$3)),-Inputs!$B$2*(1-Inputs!$B$3)),0) | J7: =H7+I7 | K7: =K6+J7
A8: 6 | B8: =12*Inputs!$B$7*POWER(1+Inputs!$B$8,A8-1) | C8: =-B8*Inputs!$B$9 | D8: =B8+C8 | E8: =-B8*Inputs!$B$10 | F8: =D8+E8 | G8: =-12*Loan!$B$2 | H8: =F8+G8 | I8: =IF(A8=Inputs!$B$11,Inputs!$B$2*POWER(1+Inputs!$B$12,Inputs!$B$11)-FV(Inputs!$B$5/100/12,Inputs!$B$11*12,PMT(Inputs!$B$5/100/12,Inputs!$B$6*12,-Inputs!$B$2*(1-Inputs!$B$3)),-Inputs!$B$2*(1-Inputs!$B$3)),0) | J8: =H8+I8 | K8: =K7+J8
A9: 7 | B9: =12*Inputs!$B$7*POWER(1+Inputs!$B$8,A9-1) | C9: =-B9*Inputs!$B$9 | D9: =B9+C9 | E9: =-B9*Inputs!$B$10 | F9: =D9+E9 | G9: =-12*Loan!$B$2 | H9: =F9+G9 | I9: =IF(A9=Inputs!$B$11,Inputs!$B$2*POWER(1+Inputs!$B$12,Inputs!$B$11)-FV(Inputs!$B$5/100/12,Inputs!$B$11*12,PMT(Inputs!$B$5/100/12,Inputs!$B$6*12,-Inputs!$B$2*(1-Inputs!$B$3)),-Inputs!$B$2*(1-Inputs!$B$3)),0) | J9: =H9+I9 | K9: =K8+J9
A10: 8 | B10: =12*Inputs!$B$7*POWER(1+Inputs!$B$8,A10-1) | C10: =-B10*Inputs!$B$9 | D10: =B10+C10 | E10: =-B10*Inputs!$B$10 | F10: =D10+E10 | G10: =-12*Loan!$B$2 | H10: =F10+G10 | I10: =IF(A10=Inputs!$B$11,Inputs!$B$2*POWER(1+Inputs!$B$12,Inputs!$B$11)-FV(Inputs!$B$5/100/12,Inputs!$B$11*12,PMT(Inputs!$B$5/100/12,Inputs!$B$6*12,-Inputs!$B$2*(1-Inputs!$B$3)),-Inputs!$B$2*(1-Inputs!$B$3)),0) | J10: =H10+I10 | K10: =K9+J10
A11: 9 | B11: =12*Inputs!$B$7*POWER(1+Inputs!$B$8,A11-1) | C11: =-B11*Inputs!$B$9 | D11: =B11+C11 | E11: =-B11*Inputs!$B$10 | F11: =D11+E11 | G11: =-12*Loan!$B$2 | H11: =F11+G11 | I11: =IF(A11=Inputs!$B$11,Inputs!$B$2*POWER(1+Inputs!$B$12,Inputs!$B$11)-FV(Inputs!$B$5/100/12,Inputs!$B$11*12,PMT(Inputs!$B$5/100/12,Inputs!$B$6*12,-Inputs!$B$2*(1-Inputs!$B$3)),-Inputs!$B$2*(1-Inputs!$B$3)),0) | J11: =H11+I11 | K11: =K10+J11
A12: 10 | B12: =12*Inputs!$B$7*POWER(1+Inputs!$B$8,A12-1) | C12: =-B12*Inputs!$B$9 | D12: =B12+C12 | E12: =-B12*Inputs!$B$10 | F12: =D12+E12 | G12: =-12*Loan!$B$2 | H12: =F12+G12 | I12: =IF(A12=Inputs!$B$11,Inputs!$B$2*POWER(1+Inputs!$B$12,Inputs!$B$11)-FV(Inputs!$B$5/100/12,Inputs!$B$11*12,PMT(Inputs!$B$5/100/12,Inputs!$B$6*12,-Inputs!$B$2*(1-Inputs!$B$3)),-Inputs!$B$2*(1-Inputs!$B$3)),0) | J12: =H12+I12 | K12: =K11+J12
A13: 11 | B13: =12*Inputs!$B$7*POWER(1+Inputs!$B$8,A13-1) | C13: =-B13*Inputs!$B$9 | D13: =B13+C13 | E13: =-B13*Inputs!$B$10 | F13: =D13+E13 | G13: =-12*Loan!$B$2 | H13: =F13+G13 | I13: =IF(A13=Inputs!$B$11,Inputs!$B$2*POWER(1+Inputs!$B$12,Inputs!$B$11)-FV(Inputs!$B$5/100/12,Inputs!$B$11*12,PMT(Inputs!$B$5/100/12,Inputs!$B$6*12,-Inputs!$B$2*(1-Inputs!$B$3)),-Inputs!$B$2*(1-Inputs!$B$3)),0) | J13: =H13+I13 | K13: =K12+J13
A14: 12 | B14: =12*Inputs!$B$7*POWER(1+Inputs!$B$8,A14-1) | C14: =-B14*Inputs!$B$9 | D14: =B14+C14 | E14: =-B14*Inputs!$B$10 | F14: =D14+E14 | G14: =-12*Loan!$B$2 | H14: =F14+G14 | I14: =IF(A14=Inputs!$B$11,Inputs!$B$2*POWER(1+Inputs!$B$12,Inputs!$B$11)-FV(Inputs!$B$5/100/12,Inputs!$B$11*12,PMT(Inputs!$B$5/100/12,Inputs!$B$6*12,-Inputs!$B$2*(1-Inputs!$B$3)),-Inputs!$B$2*(1-Inputs!$B$3)),0) | J14: =H14+I14 | K14: =K13+J14
... A27: 25 | B27: =12*Inputs!$B$7*POWER(1+Inputs!$B$8,A27-1) | C27: =-B27*Inputs!$B$9 | D27: =B27+C27 | E27: =-B27*Inputs!$B$10 | F27: =D27+E27 | G27: =-12*Loan!$B$2 | H27: =F27+G27 | I27: =IF(A27=Inputs!$B$11,Inputs!$B$2*POWER(1+Inputs!$B$12,Inputs!$B$11)-FV(Inputs!$B$5/100/12,Inputs!$B$11*12,PMT(Inputs!$B$5/100/12,Inputs!$B$6*12,-Inputs!$B$2*(1-Inputs!$B$3)),-Inputs!$B$2*(1-Inputs!$B$3)),0) | J27: =H27+I27 | K27: =K26+J27

Sheet Summary
A1: Exit (end of holding period)
A2: Item | B2: Value
A3: Sale price | B3: =Inputs!$B$2*POWER(1+Inputs!$B$12,Inputs!$B$11)
A4: Loan balance at exit | B4: =FV(Inputs!$B$5/100/12,Inputs!$B$6*12-Inputs!$B$11*12,PMT(Inputs!$B$5/100/12,Inputs!$B$6*12,-Inputs!$B$2*(1-Inputs!$B$3)),-Inputs!$B$2*(1-Inputs!$B$3))
A5: Net sale proceeds | B5: =B3-B4
A7: Equity invested (down + closing) | B7: ==Inputs!$B$2*Inputs!$B$3+Inputs!$B$2*Inputs!$B$4
A8: Total distributions (rental CF + sale) | B8: =SUM(OFFSET('Cash Flow'!J2,1,0,Inputs!$B$11,1))
A9: Net sale proceeds (at exit) | B9: =B5
A10: Total distributions (same as B8) | B10: =B8
A11: MOIC (Multiple on Invested Capital) | B11: =B10/B7
A12: ROI % | B12: =(B10-B7)/B7*100
A13: IRR % (levered, annual) | B13: =IRR(OFFSET('Cash Flow'!J2,0,0,Inputs!$B$11+1,1))*100
A14: Breakeven year (first year cumulative CF >= 0) | B14: =INDEX('Cash Flow'!A2:A25,MATCH(0,'Cash Flow'!K2:K25,1)+1)
